{
  "display": {
    "icon": {
      "item": "things:pickaxe"
    },
    "title": "The undead become dead again",
    "description": "I wasn't stronk enough",
    "frame": "task",
    "show_toast": true,
    "announce_to_chat": true
  },
  "parent": "minecraft:adventure/kill_a_mob",
  "criteria": {
    "things:stronkzombie": {
      "conditions": {
        "entity": [
          {
            "condition": "minecraft:entity_properties",
            "entity": "this",
            "predicate": {
              "type": "things:stronkzombie"
            }
          }
        ]
      },
      "trigger": "minecraft:player_killed_entity"
    }
  }
}